mocodo_magic/__init__.py
mocodo_magic/mocodo_magic.py
mocodo_magic-1.0.3.dist-info/DESCRIPTION.rst
mocodo_magic-1.0.3.dist-info/METADATA
mocodo_magic-1.0.3.dist-info/RECORD
mocodo_magic-1.0.3.dist-info/WHEEL
mocodo_magic-1.0.3.dist-info/metadata.json
mocodo_magic-1.0.3.dist-info/top_level.txt
