Metadata-Version: 2.0
Name: mocodo-magic
Version: 1.0.3
Summary: Ipython magic extension to use Mocodo in a Jupyter Notebook.
Home-page: https://github.com/laowantong/mocodo
Author: Aristide Grange
Author-email: mocodo@wingi.net
License: MIT
Keywords: relational database drawing ERD SVG
Platform: UNKNOWN
Classifier: Development Status :: 5 - Production/Stable
Classifier: Intended Audience :: Education
Classifier: Intended Audience :: Information Technology
Classifier: Topic :: Database
Classifier: License :: OSI Approved :: MIT License
Classifier: Programming Language :: Python :: 2
Classifier: Programming Language :: Python :: 2.7
Classifier: Programming Language :: Python :: 3
Classifier: Programming Language :: Python :: 3.5
Classifier: Framework :: IPython
Requires-Dist: ipython
Requires-Dist: mocodo
